{
  "meta": {
    "run_id": "20260109_201044_app_factory_run",
    "idea_id": "warrantyvault_002",
    "idea_name": "WarrantyVault",
    "idea_dir": "02_warrantyvault__warrantyvault_002",
    "source_root": "runs/2026-01-09/20260109_201044_app_factory_run/ideas/02_warrantyvault__warrantyvault_002/",
    "input_stage_paths": [
      "runs/2026-01-09/20260109_201044_app_factory_run/ideas/02_warrantyvault__warrantyvault_002/meta/idea.json",
      "runs/2026-01-09/20260109_201044_app_factory_run/ideas/02_warrantyvault__warrantyvault_002/meta/boundary.json",
      "runs/2026-01-09/20260109_201044_app_factory_run/stage01/stages/stage01.json"
    ],
    "boundary_path": "runs/2026-01-09/20260109_201044_app_factory_run/ideas/02_warrantyvault__warrantyvault_002/meta/boundary.json"
  },
  "product_specification": {
    "app_concept": {
      "name": "WarrantyVault",
      "tagline": "Never lose a warranty claim again",
      "category": "Utilities / Home",
      "core_value_proposition": "Protect your purchases by tracking warranty expiration dates with timely reminders and organized documentation for claims"
    },
    "target_users": {
      "primary": {
        "segment": "Homeowners with valuable purchases",
        "pain_points": [
          "Losing receipts and warranty documents",
          "Missing warranty expiration dates",
          "Unable to prove purchase date for claims",
          "Disorganized documentation across filing cabinets and emails"
        ],
        "goals": [
          "Never miss a warranty claim opportunity",
          "Quickly access documentation when something breaks",
          "Know at a glance what's still under warranty",
          "Have insurance-ready inventory of possessions"
        ],
        "demographics": "Adults 30-55, homeowners, household income $60K+, multiple appliances and electronics"
      },
      "secondary": {
        "segment": "Renters with expensive electronics",
        "pain_points": [
          "Frequent moves make tracking documents difficult",
          "Extended warranties purchased but forgotten",
          "No centralized place for digital receipts"
        ],
        "goals": [
          "Portable warranty tracking across moves",
          "Quick lookup when devices malfunction",
          "Simple organization without physical filing"
        ]
      }
    },
    "core_features": {
      "mvp_features": [
        {
          "name": "Quick Add Item",
          "description": "Add new items with photo of receipt, product name, purchase date, warranty period, and optional product photo",
          "user_story": "As a user, I want to quickly add a new purchase so I can start tracking its warranty immediately",
          "acceptance_criteria": [
            "Camera capture for receipt photo",
            "Manual entry fields for product details",
            "Date picker for purchase date",
            "Warranty duration selector (months/years)",
            "Optional product photo attachment",
            "Save to local storage"
          ],
          "complexity_estimate": "M"
        },
        {
          "name": "Warranty Dashboard",
          "description": "Home screen showing all items organized by warranty status: active, expiring soon, expired",
          "user_story": "As a user, I want to see all my warranties at a glance so I can quickly identify what needs attention",
          "acceptance_criteria": [
            "Section for items expiring within 30 days",
            "Section for active warranties",
            "Section for expired items",
            "Item count badges per section",
            "Pull-to-refresh functionality",
            "Search/filter capability"
          ],
          "complexity_estimate": "M"
        },
        {
          "name": "Expiration Alerts",
          "description": "Push notifications reminding users before warranty expires",
          "user_story": "As a user, I want to be reminded before my warranty expires so I can make claims or extend coverage",
          "acceptance_criteria": [
            "Default alert 30 days before expiration",
            "Configurable reminder timing per item",
            "Push notification with item name and days remaining",
            "In-app notification center for missed alerts",
            "Respect device notification settings"
          ],
          "complexity_estimate": "S"
        },
        {
          "name": "Item Detail View",
          "description": "Full details for each item including photos, documents, warranty countdown, and claim status",
          "user_story": "As a user, I want to see all details about an item so I can access everything needed for a warranty claim",
          "acceptance_criteria": [
            "Product name and photo display",
            "Receipt photo with zoom capability",
            "Warranty countdown timer (days remaining)",
            "Purchase date and price",
            "Retailer and manufacturer info",
            "Edit and delete capabilities"
          ],
          "complexity_estimate": "S"
        },
        {
          "name": "Category Organization",
          "description": "Organize items by category: Electronics, Appliances, Furniture, Vehicles, Other",
          "user_story": "As a user, I want to organize items by category so I can quickly find related items",
          "acceptance_criteria": [
            "Predefined categories with icons",
            "Filter dashboard by category",
            "Category selection during item creation",
            "Item counts per category",
            "Custom category option (premium)"
          ],
          "complexity_estimate": "S"
        },
        {
          "name": "Local Data Storage",
          "description": "All data stored locally on device for offline access and privacy",
          "user_story": "As a user, I want my data stored locally so I can access it offline and maintain privacy",
          "acceptance_criteria": [
            "SQLite/AsyncStorage for structured data",
            "Local file storage for images",
            "No account required for core features",
            "Data persists across app updates",
            "Clear indication of local-only storage"
          ],
          "complexity_estimate": "S"
        }
      ],
      "premium_features": [
        {
          "name": "Cloud Backup & Sync",
          "description": "Secure cloud backup with cross-device sync for premium subscribers",
          "justification": "Protects against device loss and enables family sharing - high value for users with significant inventory"
        },
        {
          "name": "Unlimited Items",
          "description": "Free tier limited to 10 items; premium unlocks unlimited tracking",
          "justification": "Typical household has 20+ warrantied items; limit creates natural upgrade trigger"
        },
        {
          "name": "Insurance Export",
          "description": "Generate formatted PDF report suitable for insurance claims",
          "justification": "High-value feature for disaster recovery; users actively seek this capability"
        },
        {
          "name": "Manual/Document Storage",
          "description": "Attach multiple documents per item including manuals, receipts, extended warranty certificates",
          "justification": "Centralizes all product documentation; natural extension of core value"
        },
        {
          "name": "Custom Categories & Tags",
          "description": "Create custom categories and add tags for flexible organization",
          "justification": "Power user feature for those with large inventories"
        }
      ]
    },
    "success_metrics": {
      "user_engagement": {
        "daily_active_users": "15-20% DAU/MAU ratio (utility app standard)",
        "session_length": "2-3 minutes average (quick check-ins)",
        "retention_rate": "40% D30 retention (high-value utility)"
      },
      "business_metrics": {
        "conversion_to_paid": "8-12% free to paid (strong value prop)",
        "monthly_revenue_per_user": "$0.35-0.50 ARPU (freemium model)",
        "churn_rate": "<5% monthly (sticky once items added)"
      }
    },
    "competitive_analysis": {
      "direct_competitors": [
        {
          "name": "Under My Roof",
          "strengths": ["Comprehensive home inventory", "Barcode scanning", "3D room scan"],
          "weaknesses": ["$34.99/year expensive", "Broad focus dilutes warranty tracking", "Complex for simple use case"],
          "differentiation": "WarrantyVault focuses specifically on warranty lifecycle vs general inventory"
        },
        {
          "name": "MyItems",
          "strengths": ["Receipt scanning", "10-day expiration warnings", "Document transfer to buyers"],
          "weaknesses": ["Limited warranty-specific features", "Basic alert system"],
          "differentiation": "WarrantyVault offers configurable alerts and insurance-ready exports"
        },
        {
          "name": "Nest Egg",
          "strengths": ["10 photos per item", "Affordable at $4.99"],
          "weaknesses": ["One-time purchase limits updates", "No cloud sync", "Limited free version"],
          "differentiation": "WarrantyVault subscription enables continuous improvement and cloud sync"
        },
        {
          "name": "Sortly",
          "strengths": ["Custom QR codes", "Strong organization"],
          "weaknesses": ["$24/month too expensive for consumers", "Business-focused"],
          "differentiation": "WarrantyVault is consumer-focused with accessible pricing"
        }
      ],
      "positioning": "The warranty-focused tracker that's simple enough to actually use. Unlike broad home inventory apps, WarrantyVault does one thing well: making sure you never miss a warranty claim. Affordable subscription includes cloud backup and unlimited items."
    }
  }
}
