{
  "idea_id": "breath_pace_001",
  "idea_name": "BreathPace",
  "idea_slug": "breathpace",
  "rank": 1,
  "validation_score": 8.7,
  "run_id": "20260109_132516_app_factory_run",
  "generated": "2026-01-09T13:25:16Z",
  "description": "Simple breathing exercise app that adapts session length and complexity based on user completion patterns, starting with 30-second exercises",
  "target_user": "Meditation beginners overwhelmed by complex guided apps",
  "core_loop": ["Open app", "Select current stress level (1-5)", "Follow visual breathing guide (no audio)", "Complete adaptive-length session", "Rate session difficulty", "Receive next session recommendation"],
  "mvp_complexity": "S",
  "subscription_fit": "Premium: extended session library, stress pattern analytics, Apple Health integration"
}